ids_peak_ipl/__init__.py
ids_peak_ipl/_ids_peak_ipl_python_interface.so
ids_peak_ipl/exceptions.py
ids_peak_ipl/ids_peak_ipl.py
ids_peak_ipl/libids_peak_ipl.so
ids_peak_ipl/libtbb_libcxx.so.12
ids_peak_ipl-1.17.1.0.5.dist-info/METADATA
ids_peak_ipl-1.17.1.0.5.dist-info/WHEEL
ids_peak_ipl-1.17.1.0.5.dist-info/top_level.txt
ids_peak_ipl-1.17.1.0.5.dist-info/RECORD
ids_peak_ipl-1.17.1.0.5.dist-info/licenses/LICENSE
ids_peak_ipl-1.17.1.0.5.dist-info/licenses/third_party_copyrights.txt
ids_peak_ipl-1.17.1.0.5.dist-info/licenses/third_party_licenses.txt
