Metadata-Version: 2.4
Name: ids-peak-ipl
Version: 1.17.1.0.5
Summary: ids_peak_ipl - A library for image manipulation
Author-email: IDS Imaging Development Systems GmbH <support@ids-imaging.com>
License: Proprietary
Project-URL: Homepage, https://www.ids-imaging.com
Classifier: Programming Language :: Python :: 3
Classifier: Topic :: Multimedia :: Graphics :: Capture :: Digital Camera
Classifier: Topic :: Multimedia :: Video
Requires-Python: >=3.10
License-File: LICENSE
License-File: third_party_licenses.txt
License-File: third_party_copyrights.txt
Requires-Dist: numpy
Requires-Dist: ids_peak_common<2,>=1.1.0.0
Dynamic: license-file
